{
    "swagger": "2.0",
    "info": {
        "description": "Using a service as an example",
        "title": "Go Kafka API",
        "contact": {},
        "version": "1.0"
    },
    "host": "localhost:8080",
    "basePath": "/v1",
    "paths": {
        "/tasks": {
            "post": {
                "description": "Update task",
                "consumes": [
                    "application/json"
                ],
                "produces": [
                    "application/json"
                ],
                "tags": [
                    "update_task"
                ],
                "summary": "Update task",
                "operationId": "task",
                "responses": {
                    "200": {
                        "description": "OK"
                    },
                    "500": {
                        "description": "Internal Server Error",
                        "schema": {
                            "$ref": "#/definitions/v1.response"
                        }
                    }
                }
            },
            "delete": {
                "description": "Delete task",
                "consumes": [
                    "application/json"
                ],
                "produces": [
                    "application/json"
                ],
                "tags": [
                    "delete_task"
                ],
                "summary": "Delete task",
                "operationId": "task",
                "responses": {
                    "200": {
                        "description": "OK"
                    },
                    "500": {
                        "description": "Internal Server Error",
                        "schema": {
                            "$ref": "#/definitions/v1.response"
                        }
                    }
                }
            }
        }
    },
    "definitions": {
        "v1.response": {
            "type": "object",
            "properties": {
                "error": {
                    "type": "string",
                    "example": "message"
                }
            }
        }
    }
}